fz_logger/__init__.py
fz_logger/fz_logger.py
fz_mqtt/__init__.py
fz_mqtt/fz_mqtt.py
funzin_utils-1.0.5.dist-info/METADATA
funzin_utils-1.0.5.dist-info/WHEEL
funzin_utils-1.0.5.dist-info/top_level.txt
funzin_utils-1.0.5.dist-info/RECORD
