Metadata-Version: 2.1
Name: funzin-utils
Version: 1.0.5
Summary: funzin-utils is a package that provides various utilities for python programming.
Home-page: 
Author: dnchoi
Author-email: luke.dn.choi@funzin.co.kr
License: MIT
Requires-Python: >=3
Requires-Dist: black
Requires-Dist: flake8
Requires-Dist: colorlog
Requires-Dist: paho-mqtt
